evi/__init__.py
evi/cli.py
evi/core.py
evi/streamlit_app.py
evi/frameworks/__init__.py
evi/frameworks/base.py
evi/frameworks/crewai.py
evi/frameworks/langgraph.py
evi/frameworks/react.py
evi/providers/__init__.py
evi/providers/base.py
evi/providers/gemini.py
evi/providers/openai.py
evi/templates/crewai.py.j2
evi/templates/langgraph.py.j2
evi/templates/react.py.j2
evi_ai-0.1.0.dist-info/METADATA
evi_ai-0.1.0.dist-info/WHEEL
evi_ai-0.1.0.dist-info/entry_points.txt
evi_ai-0.1.0.dist-info/licenses/LICENSE
evi_ai-0.1.0.dist-info/RECORD
