Metadata-Version: 2.4
Name: evi-ai
Version: 0.1.0
Summary: A flexible multi-agent framework code generator supporting multiple LLM providers and frameworks
Project-URL: Homepage, https://github.com/yourusername/evi-ai
Project-URL: Bug Tracker, https://github.com/yourusername/evi-ai/issues
Project-URL: Documentation, https://github.com/yourusername/evi-ai
Author: evi-ai Contributors
License: MIT
License-File: LICENSE
Classifier: Development Status :: 4 - Beta
Classifier: Intended Audience :: Developers
Classifier: License :: OSI Approved :: MIT License
Classifier: Programming Language :: Python :: 3
Classifier: Programming Language :: Python :: 3.9
Classifier: Programming Language :: Python :: 3.10
Classifier: Programming Language :: Python :: 3.11
Classifier: Topic :: Software Development :: Code Generators
Classifier: Topic :: Software Development :: Libraries :: Python Modules
Requires-Python: >=3.9
Requires-Dist: click>=8.1.0
Requires-Dist: google-generativeai>=0.3.0
Requires-Dist: jinja2>=3.1.0
Requires-Dist: openai>=1.0.0
Requires-Dist: pydantic>=2.0.0
Requires-Dist: python-dotenv>=1.0.0
Provides-Extra: all
Requires-Dist: crewai>=0.28.0; extra == 'all'
Requires-Dist: google-generativeai>=0.3.0; extra == 'all'
Requires-Dist: graphviz>=0.20.0; extra == 'all'
Requires-Dist: langchain-community>=0.0.10; extra == 'all'
Requires-Dist: langchain-core>=0.1.0; extra == 'all'
Requires-Dist: langchain-openai>=0.0.2; extra == 'all'
Requires-Dist: langchain>=0.0.300; extra == 'all'
Requires-Dist: langgraph>=0.0.20; extra == 'all'
Requires-Dist: pygments>=2.15.0; extra == 'all'
Requires-Dist: streamlit-extras>=0.3.0; extra == 'all'
Requires-Dist: streamlit>=1.30.0; extra == 'all'
Provides-Extra: crewai
Requires-Dist: crewai>=0.28.0; extra == 'crewai'
Requires-Dist: langchain-community>=0.0.10; extra == 'crewai'
Requires-Dist: langchain-openai>=0.0.2; extra == 'crewai'
Requires-Dist: langchain>=0.0.300; extra == 'crewai'
Provides-Extra: dev
Requires-Dist: black>=23.0.0; extra == 'dev'
Requires-Dist: isort>=5.12.0; extra == 'dev'
Requires-Dist: mypy>=1.0.0; extra == 'dev'
Requires-Dist: pylint>=2.17.0; extra == 'dev'
Requires-Dist: pytest>=7.0.0; extra == 'dev'
Provides-Extra: langgraph
Requires-Dist: langchain-core>=0.1.0; extra == 'langgraph'
Requires-Dist: langchain-openai>=0.0.2; extra == 'langgraph'
Requires-Dist: langchain>=0.0.300; extra == 'langgraph'
Requires-Dist: langgraph>=0.0.20; extra == 'langgraph'
Provides-Extra: react
Requires-Dist: langchain-community>=0.0.10; extra == 'react'
Requires-Dist: langchain-core>=0.1.0; extra == 'react'
Requires-Dist: langchain-openai>=0.0.2; extra == 'react'
Requires-Dist: langchain>=0.0.300; extra == 'react'
Provides-Extra: streamlit
Requires-Dist: graphviz>=0.20.0; extra == 'streamlit'
Requires-Dist: pygments>=2.15.0; extra == 'streamlit'
Requires-Dist: streamlit-extras>=0.3.0; extra == 'streamlit'
Requires-Dist: streamlit>=1.30.0; extra == 'streamlit'
